LICENSE
MANIFEST.in
README.rst
VERSION
setup.cfg
setup.py
sqlalchemy_opentracing/__init__.py
sqlalchemy_opentracing.egg-info/PKG-INFO
sqlalchemy_opentracing.egg-info/SOURCES.txt
sqlalchemy_opentracing.egg-info/dependency_links.txt
sqlalchemy_opentracing.egg-info/requires.txt
sqlalchemy_opentracing.egg-info/top_level.txt