Metadata-Version: 1.1
Name: sqlalchemy-opentracing
Version: 0.1.6
Summary: OpenTracing support for SQLAlchemy
Home-page: https://github.com/opentracing-contrib/python-sqlalchemy/
Author: Carlos Alberto Cortez
Author-email: calberto.cortez@gmail.com
License: Apache License 2.0
Download-URL: https://github.com/opentracing-contrib/python-sqlalchemy/tarball/0.1.6
Platform: any
Classifier: Intended Audience :: Developers
Classifier: License :: OSI Approved :: BSD License
Classifier: Operating System :: OS Independent
Classifier: Programming Language :: Python
Classifier: Topic :: Software Development :: Libraries :: Python Modules
